unicode_babel/__init__.py
unicode_babel/filters.py
unicode_babel/tools.py
unicode_babel-0.1.7.dist-info/METADATA
unicode_babel-0.1.7.dist-info/WHEEL
unicode_babel-0.1.7.dist-info/top_level.txt
unicode_babel-0.1.7.dist-info/RECORD
