Metadata-Version: 2.1
Name: unicode-babel
Version: 0.1.7
Summary: A tool for generating random characters/code-points
Home-page: https://github.com/phoughton/unicode_babel
Author: Peter Houghton
Author-email: pete@investigatingsoftware.co.uk
Classifier: Programming Language :: Python :: 3
Classifier: License :: OSI Approved :: MIT License
Classifier: Operating System :: OS Independent
Requires-Python: >=3.6
